zunclient/__init__.py
zunclient/api_versions.py
zunclient/client.py
zunclient/exceptions.py
zunclient/i18n.py
zunclient/shell.py
zunclient/version.py
zunclient/common/__init__.py
zunclient/common/base.py
zunclient/common/cliutils.py
zunclient/common/httpclient.py
zunclient/common/template_format.py
zunclient/common/template_utils.py
zunclient/common/utils.py
zunclient/common/apiclient/__init__.py
zunclient/common/apiclient/auth.py
zunclient/common/apiclient/base.py
zunclient/common/apiclient/exceptions.py
zunclient/common/websocketclient/__init__.py
zunclient/common/websocketclient/exceptions.py
zunclient/common/websocketclient/websocketclient.py
zunclient/osc/__init__.py
zunclient/osc/plugin.py
zunclient/osc/v1/__init__.py
zunclient/osc/v1/availability_zones.py
zunclient/osc/v1/capsules.py
zunclient/osc/v1/containers.py
zunclient/osc/v1/hosts.py
zunclient/osc/v1/images.py
zunclient/osc/v1/quota_classes.py
zunclient/osc/v1/quotas.py
zunclient/osc/v1/registries.py
zunclient/osc/v1/services.py
zunclient/tests/__init__.py
zunclient/tests/functional/__init__.py
zunclient/tests/functional/base.py
zunclient/tests/functional/hooks/__init__.py
zunclient/tests/functional/hooks/gate_hook.sh
zunclient/tests/functional/hooks/post_test_hook.sh
zunclient/tests/functional/osc/__init__.py
zunclient/tests/functional/osc/v1/__init__.py
zunclient/tests/functional/osc/v1/base.py
zunclient/tests/functional/osc/v1/test_container.py
zunclient/tests/unit/__init__.py
zunclient/tests/unit/base.py
zunclient/tests/unit/test_api_versions.py
zunclient/tests/unit/test_client.py
zunclient/tests/unit/test_shell.py
zunclient/tests/unit/test_websocketclient.py
zunclient/tests/unit/utils.py
zunclient/tests/unit/common/__init__.py
zunclient/tests/unit/common/test_httpclient.py
zunclient/tests/unit/common/test_utils.py
zunclient/tests/unit/osc/__init__.py
zunclient/tests/unit/osc/test_plugin.py
zunclient/tests/unit/v1/__init__.py
zunclient/tests/unit/v1/shell_test_base.py
python_zunclient-5.3.0.dist-info/AUTHORS
python_zunclient-5.3.0.dist-info/LICENSE
python_zunclient-5.3.0.dist-info/METADATA
python_zunclient-5.3.0.dist-info/WHEEL
python_zunclient-5.3.0.dist-info/entry_points.txt
python_zunclient-5.3.0.dist-info/pbr.json
python_zunclient-5.3.0.dist-info/top_level.txt
python_zunclient-5.3.0.dist-info/RECORD
